MANIFEST.in
README.rst
setup.py
django_hitcounter.egg-info/PKG-INFO
django_hitcounter.egg-info/SOURCES.txt
django_hitcounter.egg-info/dependency_links.txt
django_hitcounter.egg-info/top_level.txt
hitcounter/__init__.py
hitcounter/admin.py
hitcounter/models.py
hitcounter/tests.py
hitcounter/views.py
hitcounter/migrations/0001_initial.py
hitcounter/migrations/__init__.py