Metadata-Version: 1.1
Name: django-hitcounter
Version: 0.1.1
Summary: Django hitcounter tracks the number of hits/views for chosen objects
Home-page: https://github.com/TracyWebTech/django-hitcounter
Author: Tracy Web Technologies
Author-email: contato@tracy.com.br
License: BSD License
Platform: UNKNOWN
Classifier: Development Status :: 4 - Beta
Classifier: Environment :: Plugins
Classifier: Framework :: Django
Classifier: Intended Audience :: Developers
Classifier: License :: OSI Approved :: BSD License
Classifier: Programming Language :: Python
Classifier: Topic :: Software Development :: Libraries :: Python Modules
